{
  "id": "b8d5250d-b3b2-1d7e-f50b-2308f7faa263",
  "name": "VP",
  "values": [
    {
      "enabled": true,
      "key": "BearerToken",
      "value": "dnBmaXR3ZWJhcHA6SkJVWTlWRTY5MjQzQllDOTAyNDM4N0hHVlkzQVFGSw==",
      "type": "text"
    },
    {
      "enabled": true,
      "key": "accessToken",
      "value": "acf34b425936a5f10d2fd399dd28c037e0b291e7",
      "type": "text"
    }
  ],
  "timestamp": 1501371260385,
  "_postman_variable_scope": "environment",
  "_postman_exported_at": "2017-07-30T00:10:46.197Z",
  "_postman_exported_using": "Postman/5.0.2"
}